Workbook

Sheet Menu
B2: WEEKLY KPI REPORT
B3: MENU
C7: Start Date | D7: 45950 | E7: Select the start date for your 52-week template.
C9: KPI Group | D9: KPI Metric | E9: Explanation | F9: Calculation Method | G9: Aim
C10: Sales Performance | D10: Monthly Revenue | E10: Total revenue generated per month | F10: Sum | G10: Higher
C11: Sales Performance | D11: Customer Acquisition Cost (CAC) | E11: Cost to acquire one new customer | F11: Average | G11: Lower
C12: Sales Performance | D12: Conversion Rate | E12: Percentage of leads that become customers | F12: Average | G12: Higher
C13: Customer Success | D13: Customer Lifetime Value (CLV) | E13: Total revenue expected from a customer | F13: Average | G13: Higher
C14: Customer Success | D14: Customer Retention Rate | E14: Percentage of customers retained over time | F14: Average | G14: Higher
C15: Customer Success | D15: Net Promoter Score (NPS) | E15: Customer satisfaction and loyalty score | F15: Average | G15: Higher
C16: Financial Health | D16: Gross Profit Margin | E16: Revenue minus cost of goods sold percentage | F16: Average | G16: Higher
C17: Financial Health | D17: Cash Flow | E17: Net cash coming in and going out | F17: Sum | G17: Higher
C18: Operational Efficiency | D18: Average Order Value (AOV) | E18: Average amount spent per transaction | F18: Average | G18: Higher
C19: Operational Efficiency | D19: Employee Productivity | E19: Revenue generated per employee | F19: Average | G19: Higher
F20: Select the method of calculation to find cumulative totals: Sum or Average. | G20: Select the aim as "Lower" if a KPI indicates a better performance when it's numerically lower.

Sheet Report
B2: WEEKLY KPI REPORT
B3: MENU | C3: KPI REPORT
D7: =IFERROR(IF(Menu!$D10="","",Menu!$D10),"") -> Monthly Revenue | G7: =IFERROR(IF(Menu!$D11="","",Menu!$D11),"") -> Customer Acquisition Cost (CAC) | J7: =IFERROR(IF(Menu!$D12="","",Menu!$D12),"") -> Conversion Rate | M7: =IFERROR(IF(Menu!$D13="","",Menu!$D13),"") -> Customer Lifetime Value (CLV) | P7: =IFERROR(IF(Menu!$D14="","",Menu!$D14),"") -> Customer Retention Rate | S7: =IFERROR(IF(Menu!$D15="","",Menu!$D15),"") -> Net Promoter Score (NPS) | V7: =IFERROR(IF(Menu!$D16="","",Menu!$D16),"") -> Gross Profit Margin | Y7: =IFERROR(IF(Menu!$D17="","",Menu!$D17),"") -> Cash Flow | AB7: =IFERROR(IF(Menu!$D18="","",Menu!$D18),"") -> Average Order Value (AOV) | AE7: =IFERROR(IF(Menu!$D19="","",Menu!$D19),"") -> Employee Productivity
C8: Weeks | D8: Target | E8: Actual | G8: Target | H8: Actual | J8: Target | K8: Actual | M8: Target | N8: Actual | P8: Target | Q8: Actual | S8: Target | T8: Actual | V8: Target | W8: Actual | Y8: Target | Z8: Actual | AB8: Target | AC8: Actual | AE8: Target | AF8: Actual
B9: Week 1 | C9: =IFERROR(Calc!K8,"") -> 20 Oct - 26 Oct | D9: 1000 | E9: 200 | F9: =IFERROR(IF(INDEX(Menu!$G$10:$G$19,MATCH(Report!D$7,Menu!$D$10:$D$19,0))=Calc!$D$9,Report!D9/Report!E9*100,Report!E9/Report!D9*100),"") -> 20 | G9: 10 | H9: 8 | I9: =IFERROR(IF(INDEX(Menu!$G$10:$G$19,MATCH(Report!G$7,Menu!$D$10:$D$19,0))=Calc!$D$9,Report!G9/Report!H9*100,Report!H9/Report!G9*100),"") -> 125 | J9: 5 | K9: 4 | L9: =IFERROR(IF(INDEX(Menu!$G$10:$G$19,MATCH(Report!J$7,Menu!$D$10:$D$19,0))=Calc!$D$9,Report!J9/Report!K9*100,Report!K9/Report!J9*100),"") -> 80 | M9: 3000 | N9: 3500 | O9: =IFERROR(IF(INDEX(Menu!$G$10:$G$19,MATCH(Report!M$7,Menu!$D$10:$D$19,0))=Calc!$D$9,Report!M9/Report!N9*100,Report!N9/Report!M9*100),"") -> 116.66667 | P9: 30 | Q9: 25 | R9: =IFERROR(IF(INDEX(Menu!$G$10:$G$19,MATCH(Report!P$7,Menu!$D$10:$D$19,0))=Calc!$D$9,Report!P9/Report!Q9*100,Report!Q9/Report!P9*100),"") -> 83.333333 | S9: 200 | T9: 100 | U9: =IFERROR(IF(INDEX(Menu!$G$10:$G$19,MATCH(Report!S$7,Menu!$D$10:$D$19,0))=Calc!$D$9,Report!S9/Report!T9*100,Report!T9/Report!S9*100),"") -> 50 | V9: 20 | W9: 20 | X9: =IFERROR(IF(INDEX(Menu!$G$10:$G$19,MATCH(Report!V$7,Menu!$D$10:$D$19,0))=Calc!$D$9,Report!V9/Report!W9*100,Report!W9/Report!V9*100),"") -> 100 | Y9: 25000 | Z9: 25000 | AA9: =IFERROR(IF(INDEX(Menu!$G$10:$G$19,MATCH(Report!Y$7,Menu!$D$10:$D$19,0))=Calc!$D$9,Report!Y9/Report!Z9*100,Report!Z9/Report!Y9*100),"") -> 100 | AB9: 200 | AC9: 150 | AD9: =IFERROR(IF(INDEX(Menu!$G$10:$G$19,MATCH(Report!AB$7,Menu!$D$10:$D$19,0))=Calc!$D$9,Report!AB9/Report!AC9*100,Report!AC9/Report!AB9*100),"") -> 75 | AE9: 90 | AF9: 80 | AG9: =IFERROR(IF(INDEX(Menu!$G$10:$G$19,MATCH(Report!AE$7,Menu!$D$10:$D$19,0))=Calc!$D$9,Report!AE9/Report!AF9*100,Report!AF9/Report!AE9*100),"") -> 88.888889
B10: Week 2 | C10: =IFERROR(Calc!K9,"") -> 27 Oct - 2 Nov | D10: 1000 | E10: 920 | F10: =IFERROR(IF(INDEX(Menu!$G$10:$G$19,MATCH(Report!D$7,Menu!$D$10:$D$19,0))=Calc!$D$9,Report!D10/Report!E10*100,Report!E10/Report!D10*100),"") -> 92 | G10: 10 | H10: 12 | I10: =IFERROR(IF(INDEX(Menu!$G$10:$G$19,MATCH(Report!G$7,Menu!$D$10:$D$19,0))=Calc!$D$9,Report!G10/Report!H10*100,Report!H10/Report!G10*100),"") -> 83.333333 | J10: 5 | K10: 4 | L10: =IFERROR(IF(INDEX(Menu!$G$10:$G$19,MATCH(Report!J$7,Menu!$D$10:$D$19,0))=Calc!$D$9,Report!J10/Report!K10*100,Report!K10/Report!J10*100),"") -> 80 | M10: 3000 | N10: 2900 | O10: =IFERROR(IF(INDEX(Menu!$G$10:$G$19,MATCH(Report!M$7,Menu!$D$10:$D$19,0))=Calc!$D$9,Report!M10/Report!N10*100,Report!N10/Report!M10*100),"") -> 96.666667 | R10: =IFERROR(IF(INDEX(Menu!$G$10:$G$19,MATCH(Report!P$7,Menu!$D$10:$D$19,0))=Calc!$D$9,Report!P10/Report!Q10*100,Report!Q10/Report!P10*100),"") | S10: 200 | T10: 150 | U10: =IFERROR(IF(INDEX(Menu!$G$10:$G$19,MATCH(Report!S$7,Menu!$D$10:$D$19,0))=Calc!$D$9,Report!S10/Report!T10*100,Report!T10/Report!S10*100),"") -> 75 | V10: 20 | W10: 18 | X10: =IFERROR(IF(INDEX(Menu!$G$10:$G$19,MATCH(Report!V$7,Menu!$D$10:$D$19,0))=Calc!$D$9,Report!V10/Report!W10*100,Report!W10/Report!V10*100),"") -> 90 | Y10: 25000 | Z10: 18000 | AA10: =IFERROR(IF(INDEX(Menu!$G$10:$G$19,MATCH(Report!Y$7,Menu!$D$10:$D$19,0))=Calc!$D$9,Report!Y10/Report!Z10*100,Report!Z10/Report!Y10*100),"") -> 72 | AB10: 200 | AC10: 220 | AD10: =IFERROR(IF(INDEX(Menu!$G$10:$G$19,MATCH(Report!AB$7,Menu!$D$10:$D$19,0))=Calc!$D$9,Report!AB10/Report!AC10*100,Report!AC10/Report!AB10*100),"") -> 110 | AE10: 90 | AF10: 71 | AG10: =IFERROR(IF(INDEX(Menu!$G$10:$G$19,MATCH(Report!AE$7,Menu!$D$10:$D$19,0))=Calc!$D$9,Report!AE10/Report!AF10*100,Report!AF10/Report!AE10*100),"") -> 78.888889
B11: Week 3 | C11: =IFERROR(Calc!K10,"") -> 3 Nov - 9 Nov | D11: 1000 | E11: 1050 | F11: =IFERROR(IF(INDEX(Menu!$G$10:$G$19,MATCH(Report!D$7,Menu!$D$10:$D$19,0))=Calc!$D$9,Report!D11/Report!E11*100,Report!E11/Report!D11*100),"") -> 105 | G11: 10 | H11: 11 | I11: =IFERROR(IF(INDEX(Menu!$G$10:$G$19,MATCH(Report!G$7,Menu!$D$10:$D$19,0))=Calc!$D$9,Report!G11/Report!H11*100,Report!H11/Report!G11*100),"") -> 90.909091 | J11: 5 | K11: 4 | L11: =IFERROR(IF(INDEX(Menu!$G$10:$G$19,MATCH(Report!J$7,Menu!$D$10:$D$19,0))=Calc!$D$9,Report!J11/Report!K11*100,Report!K11/Report!J11*100),"") -> 80 | M11: 2000 | N11: 2000 | O11: =IFERROR(IF(INDEX(Menu!$G$10:$G$19,MATCH(Report!M$7,Menu!$D$10:$D$19,0))=Calc!$D$9,Report!M11/Report!N11*100,Report!N11/Report!M11*100),"") -> 100 | R11: =IFERROR(IF(INDEX(Menu!$G$10:$G$19,MATCH(Report!P$7,Menu!$D$10:$D$19,0))=Calc!$D$9,Report!P11/Report!Q11*100,Report!Q11/Report!P11*100),"") | U11: =IFERROR(IF(INDEX(Menu!$G$10:$G$19,MATCH(Report!S$7,Menu!$D$10:$D$19,0))=Calc!$D$9,Report!S11/Report!T11*100,Report!T11/Report!S11*100),"") | V11: 20 | W11: 25 | X11: =IFERROR(IF(INDEX(Menu!$G$10:$G$19,MATCH(Report!V$7,Menu!$D$10:$D$19,0))=Calc!$D$9,Report!V11/Report!W11*100,Report!W11/Report!V11*100),"") -> 125 | AA11: =IFERROR(IF(INDEX(Menu!$G$10:$G$19,MATCH(Report!Y$7,Menu!$D$10:$D$19,0))=Calc!$D$9,Report!Y11/Report!Z11*100,Report!Z11/Report!Y11*100),"") | AD11: =IFERROR(IF(INDEX(Menu!$G$10:$G$19,MATCH(Report!AB$7,Menu!$D$10:$D$19,0))=Calc!$D$9,Report!AB11/Report!AC11*100,Report!AC11/Report!AB11*100),"") | AG11: =IFERROR(IF(INDEX(Menu!$G$10:$G$19,MATCH(Report!AE$7,Menu!$D$10:$D$19,0))=Calc!$D$9,Report!AE11/Report!AF11*100,Report!AF11/Report!AE11*100),"")
B12: Week 4 | C12: =IFERROR(Calc!K11,"") -> 10 Nov - 16 Nov | D12: 1000 | E12: 200 | F12: =IFERROR(IF(INDEX(Menu!$G$10:$G$19,MATCH(Report!D$7,Menu!$D$10:$D$19,0))=Calc!$D$9,Report!D12/Report!E12*100,Report!E12/Report!D12*100),"") -> 20 | G12: 10 | H12: 15 | I12: =IFERROR(IF(INDEX(Menu!$G$10:$G$19,MATCH(Report!G$7,Menu!$D$10:$D$19,0))=Calc!$D$9,Report!G12/Report!H12*100,Report!H12/Report!G12*100),"") -> 66.666667 | J12: 5 | K12: 2 | L12: =IFERROR(IF(INDEX(Menu!$G$10:$G$19,MATCH(Report!J$7,Menu!$D$10:$D$19,0))=Calc!$D$9,Report!J12/Report!K12*100,Report!K12/Report!J12*100),"") -> 40 | O12: =IFERROR(IF(INDEX(Menu!$G$10:$G$19,MATCH(Report!M$7,Menu!$D$10:$D$19,0))=Calc!$D$9,Report!M12/Report!N12*100,Report!N12/Report!M12*100),"") | R12: =IFERROR(IF(INDEX(Menu!$G$10:$G$19,MATCH(Report!P$7,Menu!$D$10:$D$19,0))=Calc!$D$9,Report!P12/Report!Q12*100,Report!Q12/Report!P12*100),"") | U12: =IFERROR(IF(INDEX(Menu!$G$10:$G$19,MATCH(Report!S$7,Menu!$D$10:$D$19,0))=Calc!$D$9,Report!S12/Report!T12*100,Report!T12/Report!S12*100),"") | V12: 20 | W12: 25 | X12: =IFERROR(IF(INDEX(Menu!$G$10:$G$19,MATCH(Report!V$7,Menu!$D$10:$D$19,0))=Calc!$D$9,Report!V12/Report!W12*100,Report!W12/Report!V12*100),"") -> 125 | AA12: =IFERROR(IF(INDEX(Menu!$G$10:$G$19,MATCH(Report!Y$7,Menu!$D$10:$D$19,0))=Calc!$D$9,Report!Y12/Report!Z12*100,Report!Z12/Report!Y12*100),"") | AD12: =IFERROR(IF(INDEX(Menu!$G$10:$G$19,MATCH(Report!AB$7,Menu!$D$10:$D$19,0))=Calc!$D$9,Report!AB12/Report!AC12*100,Report!AC12/Report!AB12*100),"") | AG12: =IFERROR(IF(INDEX(Menu!$G$10:$G$19,MATCH(Report!AE$7,Menu!$D$10:$D$19,0))=Calc!$D$9,Report!AE12/Report!AF12*100,Report!AF12/Report!AE12*100),"")
B13: Week 5 | C13: =IFERROR(Calc!K12,"") -> 17 Nov - 23 Nov | D13: 1000 | E13: 2000 | F13: =IFERROR(IF(INDEX(Menu!$G$10:$G$19,MATCH(Report!D$7,Menu!$D$10:$D$19,0))=Calc!$D$9,Report!D13/Report!E13*100,Report!E13/Report!D13*100),"") -> 200 | G13: 10 | H13: 9 | I13: =IFERROR(IF(INDEX(Menu!$G$10:$G$19,MATCH(Report!G$7,Menu!$D$10:$D$19,0))=Calc!$D$9,Report!G13/Report!H13*100,Report!H13/Report!G13*100),"") -> 111.11111 | J13: 5 | K13: 2 | L13: =IFERROR(IF(INDEX(Menu!$G$10:$G$19,MATCH(Report!J$7,Menu!$D$10:$D$19,0))=Calc!$D$9,Report!J13/Report!K13*100,Report!K13/Report!J13*100),"") -> 40 | O13: =IFERROR(IF(INDEX(Menu!$G$10:$G$19,MATCH(Report!M$7,Menu!$D$10:$D$19,0))=Calc!$D$9,Report!M13/Report!N13*100,Report!N13/Report!M13*100),"") | R13: =IFERROR(IF(INDEX(Menu!$G$10:$G$19,MATCH(Report!P$7,Menu!$D$10:$D$19,0))=Calc!$D$9,Report!P13/Report!Q13*100,Report!Q13/Report!P13*100),"") | U13: =IFERROR(IF(INDEX(Menu!$G$10:$G$19,MATCH(Report!S$7,Menu!$D$10:$D$19,0))=Calc!$D$9,Report!S13/Report!T13*100,Report!T13/Report!S13*100),"") | X13: =IFERROR(IF(INDEX(Menu!$G$10:$G$19,MATCH(Report!V$7,Menu!$D$10:$D$19,0))=Calc!$D$9,Report!V13/Report!W13*100,Report!W13/Report!V13*100),"") | AA13: =IFERROR(IF(INDEX(Menu!$G$10:$G$19,MATCH(Report!Y$7,Menu!$D$10:$D$19,0))=Calc!$D$9,Report!Y13/Report!Z13*100,Report!Z13/Report!Y13*100),"") | AD13: =IFERROR(IF(INDEX(Menu!$G$10:$G$19,MATCH(Report!AB$7,Menu!$D$10:$D$19,0))=Calc!$D$9,Report!AB13/Report!AC13*100,Report!AC13/Report!AB13*100),"") | AG13: =IFERROR(IF(INDEX(Menu!$G$10:$G$19,MATCH(Report!AE$7,Menu!$D$10:$D$19,0))=Calc!$D$9,Report!AE13/Report!AF13*100,Report!AF13/Report!AE13*100),"")
B14: Week 6 | C14: =IFERROR(Calc!K13,"") -> 24 Nov - 30 Nov | D14: 1000 | E14: 250 | F14: =IFERROR(IF(INDEX(Menu!$G$10:$G$19,MATCH(Report!D$7,Menu!$D$10:$D$19,0))=Calc!$D$9,Report!D14/Report!E14*100,Report!E14/Report!D14*100),"") -> 25 | I14: =IFERROR(IF(INDEX(Menu!$G$10:$G$19,MATCH(Report!G$7,Menu!$D$10:$D$19,0))=Calc!$D$9,Report!G14/Report!H14*100,Report!H14/Report!G14*100),"") | J14: 5 | K14: 3 | L14: =IFERROR(IF(INDEX(Menu!$G$10:$G$19,MATCH(Report!J$7,Menu!$D$10:$D$19,0))=Calc!$D$9,Report!J14/Report!K14*100,Report!K14/Report!J14*100),"") -> 60 | O14: =IFERROR(IF(INDEX(Menu!$G$10:$G$19,MATCH(Report!M$7,Menu!$D$10:$D$19,0))=Calc!$D$9,Report!M14/Report!N14*100,Report!N14/Report!M14*100),"") | R14: =IFERROR(IF(INDEX(Menu!$G$10:$G$19,MATCH(Report!P$7,Menu!$D$10:$D$19,0))=Calc!$D$9,Report!P14/Report!Q14*100,Report!Q14/Report!P14*100),"") | U14: =IFERROR(IF(INDEX(Menu!$G$10:$G$19,MATCH(Report!S$7,Menu!$D$10:$D$19,0))=Calc!$D$9,Report!S14/Report!T14*100,Report!T14/Report!S14*100),"") | X14: =IFERROR(IF(INDEX(Menu!$G$10:$G$19,MATCH(Report!V$7,Menu!$D$10:$D$19,0))=Calc!$D$9,Report!V14/Report!W14*100,Report!W14/Report!V14*100),"") | AA14: =IFERROR(IF(INDEX(Menu!$G$10:$G$19,MATCH(Report!Y$7,Menu!$D$10:$D$19,0))=Calc!$D$9,Report!Y14/Report!Z14*100,Report!Z14/Report!Y14*100),"") | AD14: =IFERROR(IF(INDEX(Menu!$G$10:$G$19,MATCH(Report!AB$7,Menu!$D$10:$D$19,0))=Calc!$D$9,Report!AB14/Report!AC14*100,Report!AC14/Report!AB14*100),"") | AG14: =IFERROR(IF(INDEX(Menu!$G$10:$G$19,MATCH(Report!AE$7,Menu!$D$10:$D$19,0))=Calc!$D$9,Report!AE14/Report!AF14*100,Report!AF14/Report!AE14*100),"")
B15: Week 7 | C15: =IFERROR(Calc!K14,"") -> 1 Dec - 7 Dec | D15: 1000 | E15: 900 | F15: =IFERROR(IF(INDEX(Menu!$G$10:$G$19,MATCH(Report!D$7,Menu!$D$10:$D$19,0))=Calc!$D$9,Report!D15/Report!E15*100,Report!E15/Report!D15*100),"") -> 90 | I15: =IFERROR(IF(INDEX(Menu!$G$10:$G$19,MATCH(Report!G$7,Menu!$D$10:$D$19,0))=Calc!$D$9,Report!G15/Report!H15*100,Report!H15/Report!G15*100),"") | L15: =IFERROR(IF(INDEX(Menu!$G$10:$G$19,MATCH(Report!J$7,Menu!$D$10:$D$19,0))=Calc!$D$9,Report!J15/Report!K15*100,Report!K15/Report!J15*100),"") | O15: =IFERROR(IF(INDEX(Menu!$G$10:$G$19,MATCH(Report!M$7,Menu!$D$10:$D$19,0))=Calc!$D$9,Report!M15/Report!N15*100,Report!N15/Report!M15*100),"") | R15: =IFERROR(IF(INDEX(Menu!$G$10:$G$19,MATCH(Report!P$7,Menu!$D$10:$D$19,0))=Calc!$D$9,Report!P15/Report!Q15*100,Report!Q15/Report!P15*100),"") | U15: =IFERROR(IF(INDEX(Menu!$G$10:$G$19,MATCH(Report!S$7,Menu!$D$10:$D$19,0))=Calc!$D$9,Report!S15/Report!T15*100,Report!T15/Report!S15*100),"") | X15: =IFERROR(IF(INDEX(Menu!$G$10:$G$19,MATCH(Report!V$7,Menu!$D$10:$D$19,0))=Calc!$D$9,Report!V15/Report!W15*100,Report!W15/Report!V15*100),"") | AA15: =IFERROR(IF(INDEX(Menu!$G$10:$G$19,MATCH(Report!Y$7,Menu!$D$10:$D$19,0))=Calc!$D$9,Report!Y15/Report!Z15*100,Report!Z15/Report!Y15*100),"") | AD15: =IFERROR(IF(INDEX(Menu!$G$10:$G$19,MATCH(Report!AB$7,Menu!$D$10:$D$19,0))=Calc!$D$9,Report!AB15/Report!AC15*100,Report!AC15/Report!AB15*100),"") | AG15: =IFERROR(IF(INDEX(Menu!$G$10:$G$19,MATCH(Report!AE$7,Menu!$D$10:$D$19,0))=Calc!$D$9,Report!AE15/Report!AF15*100,Report!AF15/Report!AE15*100),"")
B16: Week 8 | C16: =IFERROR(Calc!K15,"") -> 8 Dec - 14 Dec | D16: 1000 | E16: 920 | F16: =IFERROR(IF(INDEX(Menu!$G$10:$G$19,MATCH(Report!D$7,Menu!$D$10:$D$19,0))=Calc!$D$9,Report!D16/Report!E16*100,Report!E16/Report!D16*100),"") -> 92 | I16: =IFERROR(IF(INDEX(Menu!$G$10:$G$19,MATCH(Report!G$7,Menu!$D$10:$D$19,0))=Calc!$D$9,Report!G16/Report!H16*100,Report!H16/Report!G16*100),"") | L16: =IFERROR(IF(INDEX(Menu!$G$10:$G$19,MATCH(Report!J$7,Menu!$D$10:$D$19,0))=Calc!$D$9,Report!J16/Report!K16*100,Report!K16/Report!J16*100),"") | O16: =IFERROR(IF(INDEX(Menu!$G$10:$G$19,MATCH(Report!M$7,Menu!$D$10:$D$19,0))=Calc!$D$9,Report!M16/Report!N16*100,Report!N16/Report!M16*100),"") | R16: =IFERROR(IF(INDEX(Menu!$G$10:$G$19,MATCH(Report!P$7,Menu!$D$10:$D$19,0))=Calc!$D$9,Report!P16/Report!Q16*100,Report!Q16/Report!P16*100),"") | U16: =IFERROR(IF(INDEX(Menu!$G$10:$G$19,MATCH(Report!S$7,Menu!$D$10:$D$19,0))=Calc!$D$9,Report!S16/Report!T16*100,Report!T16/Report!S16*100),"") | X16: =IFERROR(IF(INDEX(Menu!$G$10:$G$19,MATCH(Report!V$7,Menu!$D$10:$D$19,0))=Calc!$D$9,Report!V16/Report!W16*100,Report!W16/Report!V16*100),"") | AA16: =IFERROR(IF(INDEX(Menu!$G$10:$G$19,MATCH(Report!Y$7,Menu!$D$10:$D$19,0))=Calc!$D$9,Report!Y16/Report!Z16*100,Report!Z16/Report!Y16*100),"") | AD16: =IFERROR(IF(INDEX(Menu!$G$10:$G$19,MATCH(Report!AB$7,Menu!$D$10:$D$19,0))=Calc!$D$9,Report!AB16/Report!AC16*100,Report!AC16/Report!AB16*100),"") | AG16: =IFERROR(IF(INDEX(Menu!$G$10:$G$19,MATCH(Report!AE$7,Menu!$D$10:$D$19,0))=Calc!$D$9,Report!AE16/Report!AF16*100,Report!AF16/Report!AE16*100),"")
B17: Week 9 | C17: =IFERROR(Calc!K16,"") -> 15 Dec - 21 Dec | D17: 1000 | E17: 930 | F17: =IFERROR(IF(INDEX(Menu!$G$10:$G$19,MATCH(Report!D$7,Menu!$D$10:$D$19,0))=Calc!$D$9,Report!D17/Report!E17*100,Report!E17/Report!D17*100),"") -> 93 | I17: =IFERROR(IF(INDEX(Menu!$G$10:$G$19,MATCH(Report!G$7,Menu!$D$10:$D$19,0))=Calc!$D$9,Report!G17/Report!H17*100,Report!H17/Report!G17*100),"") | L17: =IFERROR(IF(INDEX(Menu!$G$10:$G$19,MATCH(Report!J$7,Menu!$D$10:$D$19,0))=Calc!$D$9,Report!J17/Report!K17*100,Report!K17/Report!J17*100),"") | O17: =IFERROR(IF(INDEX(Menu!$G$10:$G$19,MATCH(Report!M$7,Menu!$D$10:$D$19,0))=Calc!$D$9,Report!M17/Report!N17*100,Report!N17/Report!M17*100),"") | R17: =IFERROR(IF(INDEX(Menu!$G$10:$G$19,MATCH(Report!P$7,Menu!$D$10:$D$19,0))=Calc!$D$9,Report!P17/Report!Q17*100,Report!Q17/Report!P17*100),"") | U17: =IFERROR(IF(INDEX(Menu!$G$10:$G$19,MATCH(Report!S$7,Menu!$D$10:$D$19,0))=Calc!$D$9,Report!S17/Report!T17*100,Report!T17/Report!S17*100),"") | X17: =IFERROR(IF(INDEX(Menu!$G$10:$G$19,MATCH(Report!V$7,Menu!$D$10:$D$19,0))=Calc!$D$9,Report!V17/Report!W17*100,Report!W17/Report!V17*100),"") | AA17: =IFERROR(IF(INDEX(Menu!$G$10:$G$19,MATCH(Report!Y$7,Menu!$D$10:$D$19,0))=Calc!$D$9,Report!Y17/Report!Z17*100,Report!Z17/Report!Y17*100),"") | AD17: =IFERROR(IF(INDEX(Menu!$G$10:$G$19,MATCH(Report!AB$7,Menu!$D$10:$D$19,0))=Calc!$D$9,Report!AB17/Report!AC17*100,Report!AC17/Report!AB17*100),"") | AG17: =IFERROR(IF(INDEX(Menu!$G$10:$G$19,MATCH(Report!AE$7,Menu!$D$10:$D$19,0))=Calc!$D$9,Report!AE17/Report!AF17*100,Report!AF17/Report!AE17*100),"")
B18: Week 10 | C18: =IFERROR(Calc!K17,"") -> 22 Dec - 28 Dec | F18: =IFERROR(IF(INDEX(Menu!$G$10:$G$19,MATCH(Report!D$7,Menu!$D$10:$D$19,0))=Calc!$D$9,Report!D18/Report!E18*100,Report!E18/Report!D18*100),"") | I18: =IFERROR(IF(INDEX(Menu!$G$10:$G$19,MATCH(Report!G$7,Menu!$D$10:$D$19,0))=Calc!$D$9,Report!G18/Report!H18*100,Report!H18/Report!G18*100),"") | L18: =IFERROR(IF(INDEX(Menu!$G$10:$G$19,MATCH(Report!J$7,Menu!$D$10:$D$19,0))=Calc!$D$9,Report!J18/Report!K18*100,Report!K18/Report!J18*100),"") | O18: =IFERROR(IF(INDEX(Menu!$G$10:$G$19,MATCH(Report!M$7,Menu!$D$10:$D$19,0))=Calc!$D$9,Report!M18/Report!N18*100,Report!N18/Report!M18*100),"") | R18: =IFERROR(IF(INDEX(Menu!$G$10:$G$19,MATCH(Report!P$7,Menu!$D$10:$D$19,0))=Calc!$D$9,Report!P18/Report!Q18*100,Report!Q18/Report!P18*100),"") | U18: =IFERROR(IF(INDEX(Menu!$G$10:$G$19,MATCH(Report!S$7,Menu!$D$10:$D$19,0))=Calc!$D$9,Report!S18/Report!T18*100,Report!T18/Report!S18*100),"") | X18: =IFERROR(IF(INDEX(Menu!$G$10:$G$19,MATCH(Report!V$7,Menu!$D$10:$D$19,0))=Calc!$D$9,Report!V18/Report!W18*100,Report!W18/Report!V18*100),"") | AA18: =IFERROR(IF(INDEX(Menu!$G$10:$G$19,MATCH(Report!Y$7,Menu!$D$10:$D$19,0))=Calc!$D$9,Report!Y18/Report!Z18*100,Report!Z18/Report!Y18*100),"") | AD18: =IFERROR(IF(INDEX(Menu!$G$10:$G$19,MATCH(Report!AB$7,Menu!$D$10:$D$19,0))=Calc!$D$9,Report!AB18/Report!AC18*100,Report!AC18/Report!AB18*100),"") | AG18: =IFERROR(IF(INDEX(Menu!$G$10:$G$19,MATCH(Report!AE$7,Menu!$D$10:$D$19,0))=Calc!$D$9,Report!AE18/Report!AF18*100,Report!AF18/Report!AE18*100),"")
B19: Week 11 | C19: =IFERROR(Calc!K18,"") -> 29 Dec - 4 Jan
B20: Week 12 | C20: =IFERROR(Calc!K19,"") -> 5 Jan - 11 Jan
B21: Week 13 | C21: =IFERROR(Calc!K20,"") -> 12 Jan - 18 Jan
B22: Week 14 | C22: =IFERROR(Calc!K21,"") -> 19 Jan - 25 Jan
B23: Week 15 | C23: =IFERROR(Calc!K22,"") -> 26 Jan - 1 Feb
B24: Week 16 | C24: =IFERROR(Calc!K23,"") -> 2 Feb - 8 Feb
B25: Week 17 | C25: =IFERROR(Calc!K24,"") -> 9 Feb - 15 Feb
B26: Week 18 | C26: =IFERROR(Calc!K25,"") -> 16 Feb - 22 Feb
B27: Week 19 | C27: =IFERROR(Calc!K26,"") -> 23 Feb - 1 Mar
B28: Week 20 | C28: =IFERROR(Calc!K27,"") -> 2 Mar - 8 Mar
B29: Week 21 | C29: =IFERROR(Calc!K28,"") -> 9 Mar - 15 Mar
B30: Week 22 | C30: =IFERROR(Calc!K29,"") -> 16 Mar - 22 Mar
... B60: Week 52 | C60: =IFERROR(Calc!K59,"") -> 12 Oct - 18 Oct

Sheet ToU
B2: TERMS OF USE
B3: END USER LICENSE AGREEMENT
B5: This End-User License Agreement is a legal agreement between you and someka.net that covers all Microsoft Excel templates, spreadsheets or software built by someka.net.
B7: By downloading, copying, accessing or otherwise using any of these templates, you agree to abide by the following terms:
B9: * You may NOT sell, resell, license, rent, lease, lend or otherwise transfer for value without written permission of someka.net * Unless you've purchased the proper license rights, you may NOT remove or alter any someka.net logo, trademark, copyright, disclaimer, brand, terms of use, attribution, or other proprietary notices or marks within the template. * You may NOT distribute, publish to an online gallery, host on a website, or place on any server in a way that makes it available to the general public.
B11: RESERVATION OF RIGHTS
B13: All title and copyrights in and to the Template, and any copies of the Template, are owned by someka.net. All rights not expressly granted are reserved by someka.net. Use of any Template for any purpose other than expressly permitted in this EULA is prohibited, and may result in severe civil and criminal penalties.
B15: CONTACT
B16: For more information and specific permissions for your case, please contact us at: contact@someka.net

Sheet Calc
B3: Dropdown Menus | H3: Date Calculations | M3: KPI Charts
I5: Start date | J5: =IFERROR(IF(Menu!$D$7="",TODAY(),Menu!$D$7),"") -> 45950 | Q5: Offset Increment | R5: 3
B7: Calculation | D7: Aim | F7: Months | H7: Index | I7: Week Start | J7: Week End | K7: Week | M7: Group | N7: KPI | O7: Calc | P7: Aim | Q7: Target Offset | R7: Actual Offset | S7: Cumulative Target | T7: Cumulative Actual | U7: Index | V7: Remaining
B8: Sum | D8: Higher | F8: Jan | H8: 1 | I8: =IFERROR($J$5,"") -> 45950 | J8: =IFERROR(I8+6,"") -> 45956 | K8: {=IFERROR(DAY(I8)&" "&INDEX($F$8:$F$19,MONTH(I8))&" - "&DAY(J8)&" "&INDEX($F$8:$F$19,MONTH(J8)),"")} -> 20 Oct - 26 Oct | M8: =IFERROR(IF(Menu!C10="","",Menu!C10),"") -> Sales Performance | N8: =IFERROR(IF(Menu!D10="","",Menu!D10),"") -> Monthly Revenue | O8: =IFERROR(IF(Menu!F10="","",Menu!F10),"") -> Sum | P8: =IFERROR(IF(Menu!G10="","",Menu!G10),"") -> Higher | Q8: 1 | R8: 2 | S8: =IFERROR(IF(N8="","",IF(O8=$B$9,AVERAGE(OFFSET(Report!$C$9,0,Calc!Q8,10.1)),SUM(OFFSET(Report!$C$9,0,Calc!Q8,10.1)))),"") -> 9000 | T8: =IFERROR(IF(N8="","",IF(O8=$B$9,AVERAGE(OFFSET(Report!$C$9,0,Calc!R8,10.1)),SUM(OFFSET(Report!$C$9,0,Calc!R8,10.1)))),"") -> 7370 | U8: =IFERROR(IF(N8="","",IF(P8=$D$9,S8/T8*100,T8/S8*100)),100) -> 81.888889 | V8: =IFERROR(IF(U8>=100,0,100-U8),"") -> 18.111111
B9: Average | D9: Lower | F9: Feb | H9: 2 | I9: =IFERROR(J8+1,"") -> 45957 | J9: =IFERROR(I9+6,"") -> 45963 | K9: {=IFERROR(DAY(I9)&" "&INDEX($F$8:$F$19,MONTH(I9))&" - "&DAY(J9)&" "&INDEX($F$8:$F$19,MONTH(J9)),"")} -> 27 Oct - 2 Nov | M9: =IFERROR(IF(Menu!C11="","",Menu!C11),"") -> Sales Performance | N9: =IFERROR(IF(Menu!D11="","",Menu!D11),"") -> Customer Acquisition Cost (CAC) | O9: =IFERROR(IF(Menu!F11="","",Menu!F11),"") -> Average | P9: =IFERROR(IF(Menu!G11="","",Menu!G11),"") -> Lower | Q9: =Q8+$R$5 -> 4 | R9: =R8+$R$5 -> 5 | S9: =IFERROR(IF(N9="","",IF(O9=$B$9,AVERAGE(OFFSET(Report!$C$9,0,Calc!Q9,10.1)),SUM(OFFSET(Report!$C$9,0,Calc!Q9,10.1)))),"") -> 10 | T9: =IFERROR(IF(N9="","",IF(O9=$B$9,AVERAGE(OFFSET(Report!$C$9,0,Calc!R9,10.1)),SUM(OFFSET(Report!$C$9,0,Calc!R9,10.1)))),"") -> 11 | U9: =IFERROR(IF(N9="","",IF(P9=$D$9,S9/T9*100,T9/S9*100)),100) -> 90.909091 | V9: =IFERROR(IF(U9>=100,0,100-U9),"") -> 9.0909091
F10: Mar | H10: 3 | I10: =IFERROR(J9+1,"") -> 45964 | J10: =IFERROR(I10+6,"") -> 45970 | K10: {=IFERROR(DAY(I10)&" "&INDEX($F$8:$F$19,MONTH(I10))&" - "&DAY(J10)&" "&INDEX($F$8:$F$19,MONTH(J10)),"")} -> 3 Nov - 9 Nov | M10: =IFERROR(IF(Menu!C12="","",Menu!C12),"") -> Sales Performance | N10: =IFERROR(IF(Menu!D12="","",Menu!D12),"") -> Conversion Rate | O10: =IFERROR(IF(Menu!F12="","",Menu!F12),"") -> Average | P10: =IFERROR(IF(Menu!G12="","",Menu!G12),"") -> Higher | Q10: =Q9+$R$5 -> 7 | R10: =R9+$R$5 -> 8 | S10: =IFERROR(IF(N10="","",IF(O10=$B$9,AVERAGE(OFFSET(Report!$C$9,0,Calc!Q10,10.1)),SUM(OFFSET(Report!$C$9,0,Calc!Q10,10.1)))),"") -> 5 | T10: =IFERROR(IF(N10="","",IF(O10=$B$9,AVERAGE(OFFSET(Report!$C$9,0,Calc!R10,10.1)),SUM(OFFSET(Report!$C$9,0,Calc!R10,10.1)))),"") -> 3.1666667 | U10: =IFERROR(IF(N10="","",IF(P10=$D$9,S10/T10*100,T10/S10*100)),100) -> 63.333333 | V10: =IFERROR(IF(U10>=100,0,100-U10),"") -> 36.666667
F11: Apr | H11: 4 | I11: =IFERROR(J10+1,"") -> 45971 | J11: =IFERROR(I11+6,"") -> 45977 | K11: {=IFERROR(DAY(I11)&" "&INDEX($F$8:$F$19,MONTH(I11))&" - "&DAY(J11)&" "&INDEX($F$8:$F$19,MONTH(J11)),"")} -> 10 Nov - 16 Nov | M11: =IFERROR(IF(Menu!C13="","",Menu!C13),"") -> Customer Success | N11: =IFERROR(IF(Menu!D13="","",Menu!D13),"") -> Customer Lifetime Value (CLV) | O11: =IFERROR(IF(Menu!F13="","",Menu!F13),"") -> Average | P11: =IFERROR(IF(Menu!G13="","",Menu!G13),"") -> Higher | Q11: =Q10+$R$5 -> 10 | R11: =R10+$R$5 -> 11 | S11: =IFERROR(IF(N11="","",IF(O11=$B$9,AVERAGE(OFFSET(Report!$C$9,0,Calc!Q11,10.1)),SUM(OFFSET(Report!$C$9,0,Calc!Q11,10.1)))),"") -> 2666.6667 | T11: =IFERROR(IF(N11="","",IF(O11=$B$9,AVERAGE(OFFSET(Report!$C$9,0,Calc!R11,10.1)),SUM(OFFSET(Report!$C$9,0,Calc!R11,10.1)))),"") -> 2800 | U11: =IFERROR(IF(N11="","",IF(P11=$D$9,S11/T11*100,T11/S11*100)),100) -> 105 | V11: =IFERROR(IF(U11>=100,0,100-U11),"") -> 0
F12: May | H12: 5 | I12: =IFERROR(J11+1,"") -> 45978 | J12: =IFERROR(I12+6,"") -> 45984 | K12: {=IFERROR(DAY(I12)&" "&INDEX($F$8:$F$19,MONTH(I12))&" - "&DAY(J12)&" "&INDEX($F$8:$F$19,MONTH(J12)),"")} -> 17 Nov - 23 Nov | M12: =IFERROR(IF(Menu!C14="","",Menu!C14),"") -> Customer Success | N12: =IFERROR(IF(Menu!D14="","",Menu!D14),"") -> Customer Retention Rate | O12: =IFERROR(IF(Menu!F14="","",Menu!F14),"") -> Average | P12: =IFERROR(IF(Menu!G14="","",Menu!G14),"") -> Higher | Q12: =Q11+$R$5 -> 13 | R12: =R11+$R$5 -> 14 | S12: =IFERROR(IF(N12="","",IF(O12=$B$9,AVERAGE(OFFSET(Report!$C$9,0,Calc!Q12,10.1)),SUM(OFFSET(Report!$C$9,0,Calc!Q12,10.1)))),"") -> 30 | T12: =IFERROR(IF(N12="","",IF(O12=$B$9,AVERAGE(OFFSET(Report!$C$9,0,Calc!R12,10.1)),SUM(OFFSET(Report!$C$9,0,Calc!R12,10.1)))),"") -> 25 | U12: =IFERROR(IF(N12="","",IF(P12=$D$9,S12/T12*100,T12/S12*100)),100) -> 83.333333 | V12: =IFERROR(IF(U12>=100,0,100-U12),"") -> 16.666667
F13: Jun | H13: 6 | I13: =IFERROR(J12+1,"") -> 45985 | J13: =IFERROR(I13+6,"") -> 45991 | K13: {=IFERROR(DAY(I13)&" "&INDEX($F$8:$F$19,MONTH(I13))&" - "&DAY(J13)&" "&INDEX($F$8:$F$19,MONTH(J13)),"")} -> 24 Nov - 30 Nov | M13: =IFERROR(IF(Menu!C15="","",Menu!C15),"") -> Customer Success | N13: =IFERROR(IF(Menu!D15="","",Menu!D15),"") -> Net Promoter Score (NPS) | O13: =IFERROR(IF(Menu!F15="","",Menu!F15),"") -> Average | P13: =IFERROR(IF(Menu!G15="","",Menu!G15),"") -> Higher | Q13: =Q12+$R$5 -> 16 | R13: =R12+$R$5 -> 17 | S13: =IFERROR(IF(N13="","",IF(O13=$B$9,AVERAGE(OFFSET(Report!$C$9,0,Calc!Q13,10.1)),SUM(OFFSET(Report!$C$9,0,Calc!Q13,10.1)))),"") -> 200 | T13: =IFERROR(IF(N13="","",IF(O13=$B$9,AVERAGE(OFFSET(Report!$C$9,0,Calc!R13,10.1)),SUM(OFFSET(Report!$C$9,0,Calc!R13,10.1)))),"") -> 125 | U13: =IFERROR(IF(N13="","",IF(P13=$D$9,S13/T13*100,T13/S13*100)),100) -> 62.5 | V13: =IFERROR(IF(U13>=100,0,100-U13),"") -> 37.5
F14: Jul | H14: 7 | I14: =IFERROR(J13+1,"") -> 45992 | J14: =IFERROR(I14+6,"") -> 45998 | K14: {=IFERROR(DAY(I14)&" "&INDEX($F$8:$F$19,MONTH(I14))&" - "&DAY(J14)&" "&INDEX($F$8:$F$19,MONTH(J14)),"")} -> 1 Dec - 7 Dec | M14: =IFERROR(IF(Menu!C16="","",Menu!C16),"") -> Financial Health | N14: =IFERROR(IF(Menu!D16="","",Menu!D16),"") -> Gross Profit Margin | O14: =IFERROR(IF(Menu!F16="","",Menu!F16),"") -> Average | P14: =IFERROR(IF(Menu!G16="","",Menu!G16),"") -> Higher | Q14: =Q13+$R$5 -> 19 | R14: =R13+$R$5 -> 20 | S14: =IFERROR(IF(N14="","",IF(O14=$B$9,AVERAGE(OFFSET(Report!$C$9,0,Calc!Q14,10.1)),SUM(OFFSET(Report!$C$9,0,Calc!Q14,10.1)))),"") -> 20 | T14: =IFERROR(IF(N14="","",IF(O14=$B$9,AVERAGE(OFFSET(Report!$C$9,0,Calc!R14,10.1)),SUM(OFFSET(Report!$C$9,0,Calc!R14,10.1)))),"") -> 22 | U14: =IFERROR(IF(N14="","",IF(P14=$D$9,S14/T14*100,T14/S14*100)),100) -> 110 | V14: =IFERROR(IF(U14>=100,0,100-U14),"") -> 0
F15: Aug | H15: 8 | I15: =IFERROR(J14+1,"") -> 45999 | J15: =IFERROR(I15+6,"") -> 46005 | K15: {=IFERROR(DAY(I15)&" "&INDEX($F$8:$F$19,MONTH(I15))&" - "&DAY(J15)&" "&INDEX($F$8:$F$19,MONTH(J15)),"")} -> 8 Dec - 14 Dec | M15: =IFERROR(IF(Menu!C17="","",Menu!C17),"") -> Financial Health | N15: =IFERROR(IF(Menu!D17="","",Menu!D17),"") -> Cash Flow | O15: =IFERROR(IF(Menu!F17="","",Menu!F17),"") -> Sum | P15: =IFERROR(IF(Menu!G17="","",Menu!G17),"") -> Higher | Q15: =Q14+$R$5 -> 22 | R15: =R14+$R$5 -> 23 | S15: =IFERROR(IF(N15="","",IF(O15=$B$9,AVERAGE(OFFSET(Report!$C$9,0,Calc!Q15,10.1)),SUM(OFFSET(Report!$C$9,0,Calc!Q15,10.1)))),"") -> 50000 | T15: =IFERROR(IF(N15="","",IF(O15=$B$9,AVERAGE(OFFSET(Report!$C$9,0,Calc!R15,10.1)),SUM(OFFSET(Report!$C$9,0,Calc!R15,10.1)))),"") -> 43000 | U15: =IFERROR(IF(N15="","",IF(P15=$D$9,S15/T15*100,T15/S15*100)),100) -> 86 | V15: =IFERROR(IF(U15>=100,0,100-U15),"") -> 14
F16: Sep | H16: 9 | I16: =IFERROR(J15+1,"") -> 46006 | J16: =IFERROR(I16+6,"") -> 46012 | K16: {=IFERROR(DAY(I16)&" "&INDEX($F$8:$F$19,MONTH(I16))&" - "&DAY(J16)&" "&INDEX($F$8:$F$19,MONTH(J16)),"")} -> 15 Dec - 21 Dec | M16: =IFERROR(IF(Menu!C18="","",Menu!C18),"") -> Operational Efficiency | N16: =IFERROR(IF(Menu!D18="","",Menu!D18),"") -> Average Order Value (AOV) | O16: =IFERROR(IF(Menu!F18="","",Menu!F18),"") -> Average | P16: =IFERROR(IF(Menu!G18="","",Menu!G18),"") -> Higher | Q16: =Q15+$R$5 -> 25 | R16: =R15+$R$5 -> 26 | S16: =IFERROR(IF(N16="","",IF(O16=$B$9,AVERAGE(OFFSET(Report!$C$9,0,Calc!Q16,10.1)),SUM(OFFSET(Report!$C$9,0,Calc!Q16,10.1)))),"") -> 200 | T16: =IFERROR(IF(N16="","",IF(O16=$B$9,AVERAGE(OFFSET(Report!$C$9,0,Calc!R16,10.1)),SUM(OFFSET(Report!$C$9,0,Calc!R16,10.1)))),"") -> 185 | U16: =IFERROR(IF(N16="","",IF(P16=$D$9,S16/T16*100,T16/S16*100)),100) -> 92.5 | V16: =IFERROR(IF(U16>=100,0,100-U16),"") -> 7.5
F17: Oct | H17: 10 | I17: =IFERROR(J16+1,"") -> 46013 | J17: =IFERROR(I17+6,"") -> 46019 | K17: {=IFERROR(DAY(I17)&" "&INDEX($F$8:$F$19,MONTH(I17))&" - "&DAY(J17)&" "&INDEX($F$8:$F$19,MONTH(J17)),"")} -> 22 Dec - 28 Dec | M17: =IFERROR(IF(Menu!C19="","",Menu!C19),"") -> Operational Efficiency | N17: =IFERROR(IF(Menu!D19="","",Menu!D19),"") -> Employee Productivity | O17: =IFERROR(IF(Menu!F19="","",Menu!F19),"") -> Average | P17: =IFERROR(IF(Menu!G19="","",Menu!G19),"") -> Higher | Q17: =Q16+$R$5 -> 28 | R17: =R16+$R$5 -> 29 | S17: =IFERROR(IF(N17="","",IF(O17=$B$9,AVERAGE(OFFSET(Report!$C$9,0,Calc!Q17,10.1)),SUM(OFFSET(Report!$C$9,0,Calc!Q17,10.1)))),"") -> 90 | T17: =IFERROR(IF(N17="","",IF(O17=$B$9,AVERAGE(OFFSET(Report!$C$9,0,Calc!R17,10.1)),SUM(OFFSET(Report!$C$9,0,Calc!R17,10.1)))),"") -> 75.5 | U17: =IFERROR(IF(N17="","",IF(P17=$D$9,S17/T17*100,T17/S17*100)),100) -> 83.888889 | V17: =IFERROR(IF(U17>=100,0,100-U17),"") -> 16.111111
F18: Nov | H18: 11 | I18: =IFERROR(J17+1,"") -> 46020 | J18: =IFERROR(I18+6,"") -> 46026 | K18: {=IFERROR(DAY(I18)&" "&INDEX($F$8:$F$19,MONTH(I18))&" - "&DAY(J18)&" "&INDEX($F$8:$F$19,MONTH(J18)),"")} -> 29 Dec - 4 Jan
F19: Dec | H19: 12 | I19: =IFERROR(J18+1,"") -> 46027 | J19: =IFERROR(I19+6,"") -> 46033 | K19: {=IFERROR(DAY(I19)&" "&INDEX($F$8:$F$19,MONTH(I19))&" - "&DAY(J19)&" "&INDEX($F$8:$F$19,MONTH(J19)),"")} -> 5 Jan - 11 Jan | N19: Index | O19: =IFERROR(MAX(COUNTIF(N8:N17,"?*"),1),"") -> 10
H20: 13 | I20: =IFERROR(J19+1,"") -> 46034 | J20: =IFERROR(I20+6,"") -> 46040 | K20: {=IFERROR(DAY(I20)&" "&INDEX($F$8:$F$19,MONTH(I20))&" - "&DAY(J20)&" "&INDEX($F$8:$F$19,MONTH(J20)),"")} -> 12 Jan - 18 Jan
H21: 14 | I21: =IFERROR(J20+1,"") -> 46041 | J21: =IFERROR(I21+6,"") -> 46047 | K21: {=IFERROR(DAY(I21)&" "&INDEX($F$8:$F$19,MONTH(I21))&" - "&DAY(J21)&" "&INDEX($F$8:$F$19,MONTH(J21)),"")} -> 19 Jan - 25 Jan
H22: 15 | I22: =IFERROR(J21+1,"") -> 46048 | J22: =IFERROR(I22+6,"") -> 46054 | K22: {=IFERROR(DAY(I22)&" "&INDEX($F$8:$F$19,MONTH(I22))&" - "&DAY(J22)&" "&INDEX($F$8:$F$19,MONTH(J22)),"")} -> 26 Jan - 1 Feb
H23: 16 | I23: =IFERROR(J22+1,"") -> 46055 | J23: =IFERROR(I23+6,"") -> 46061 | K23: {=IFERROR(DAY(I23)&" "&INDEX($F$8:$F$19,MONTH(I23))&" - "&DAY(J23)&" "&INDEX($F$8:$F$19,MONTH(J23)),"")} -> 2 Feb - 8 Feb
H24: 17 | I24: =IFERROR(J23+1,"") -> 46062 | J24: =IFERROR(I24+6,"") -> 46068 | K24: {=IFERROR(DAY(I24)&" "&INDEX($F$8:$F$19,MONTH(I24))&" - "&DAY(J24)&" "&INDEX($F$8:$F$19,MONTH(J24)),"")} -> 9 Feb - 15 Feb
H25: 18 | I25: =IFERROR(J24+1,"") -> 46069 | J25: =IFERROR(I25+6,"") -> 46075 | K25: {=IFERROR(DAY(I25)&" "&INDEX($F$8:$F$19,MONTH(I25))&" - "&DAY(J25)&" "&INDEX($F$8:$F$19,MONTH(J25)),"")} -> 16 Feb - 22 Feb
H26: 19 | I26: =IFERROR(J25+1,"") -> 46076 | J26: =IFERROR(I26+6,"") -> 46082 | K26: {=IFERROR(DAY(I26)&" "&INDEX($F$8:$F$19,MONTH(I26))&" - "&DAY(J26)&" "&INDEX($F$8:$F$19,MONTH(J26)),"")} -> 23 Feb - 1 Mar
H27: 20 | I27: =IFERROR(J26+1,"") -> 46083 | J27: =IFERROR(I27+6,"") -> 46089 | K27: {=IFERROR(DAY(I27)&" "&INDEX($F$8:$F$19,MONTH(I27))&" - "&DAY(J27)&" "&INDEX($F$8:$F$19,MONTH(J27)),"")} -> 2 Mar - 8 Mar
H28: 21 | I28: =IFERROR(J27+1,"") -> 46090 | J28: =IFERROR(I28+6,"") -> 46096 | K28: {=IFERROR(DAY(I28)&" "&INDEX($F$8:$F$19,MONTH(I28))&" - "&DAY(J28)&" "&INDEX($F$8:$F$19,MONTH(J28)),"")} -> 9 Mar - 15 Mar
H29: 22 | I29: =IFERROR(J28+1,"") -> 46097 | J29: =IFERROR(I29+6,"") -> 46103 | K29: {=IFERROR(DAY(I29)&" "&INDEX($F$8:$F$19,MONTH(I29))&" - "&DAY(J29)&" "&INDEX($F$8:$F$19,MONTH(J29)),"")} -> 16 Mar - 22 Mar
H30: 23 | I30: =IFERROR(J29+1,"") -> 46104 | J30: =IFERROR(I30+6,"") -> 46110 | K30: {=IFERROR(DAY(I30)&" "&INDEX($F$8:$F$19,MONTH(I30))&" - "&DAY(J30)&" "&INDEX($F$8:$F$19,MONTH(J30)),"")} -> 23 Mar - 29 Mar
H31: 24 | I31: =IFERROR(J30+1,"") -> 46111 | J31: =IFERROR(I31+6,"") -> 46117 | K31: {=IFERROR(DAY(I31)&" "&INDEX($F$8:$F$19,MONTH(I31))&" - "&DAY(J31)&" "&INDEX($F$8:$F$19,MONTH(J31)),"")} -> 30 Mar - 5 Apr
... H59: 52 | I59: =IFERROR(J58+1,"") -> 46307 | J59: =IFERROR(I59+6,"") -> 46313 | K59: {=IFERROR(DAY(I59)&" "&INDEX($F$8:$F$19,MONTH(I59))&" - "&DAY(J59)&" "&INDEX($F$8:$F$19,MONTH(J59)),"")} -> 12 Oct - 18 Oct
